LICENSE.md
README.md
ankh/__init__.py
ankh/extract.py
ankh/models/__init__.py
ankh/models/ankh_transformers.py
ankh/models/convbert_binary_classification.py
ankh/models/convbert_multiclass_classification.py
ankh/models/convbert_multilabel_classification.py
ankh/models/convbert_regression.py
ankh/models/layers.py
ankh/utils.py
ankh-1.10.0.dist-info/LICENSE.md
ankh-1.10.0.dist-info/METADATA
ankh-1.10.0.dist-info/WHEEL
ankh-1.10.0.dist-info/RECORD
