Metadata-Version: 2.1
Name: ankh
Version: 1.10.0
Summary: Optimized Protein Language Model
Home-page: https://github.com/agemagician/Ankh
License: CC-BY-NC-SA-4.0
Keywords: ankh
Author: Ahmed Elnaggar
Author-email: amit.najjar@gmail.com
Requires-Python: >=3.7,<4.0
Classifier: License :: Other/Proprietary License
Classifier: Programming Language :: Python :: 3
Classifier: Programming Language :: Python :: 3.7
Classifier: Programming Language :: Python :: 3.8
Classifier: Programming Language :: Python :: 3.9
Classifier: Programming Language :: Python :: 3.10
Classifier: Programming Language :: Python :: 3.11
Requires-Dist: biopython (>=1.80,<2.0)
Requires-Dist: datasets (>=2.7.1,<3.0.0)
Requires-Dist: sentencepiece (>=0.1.97,<0.2.0)
Requires-Dist: transformers (>=4.25.1,<5.0.0)
Project-URL: Repository, https://github.com/agemagician/Ankh
